trello_loader/__init__.py
trello_loader/trello_to_markdown.py
trello_loader-0.1.0.dist-info/METADATA
trello_loader-0.1.0.dist-info/WHEEL
trello_loader-0.1.0.dist-info/entry_points.txt
trello_loader-0.1.0.dist-info/licenses/LICENSE
trello_loader-0.1.0.dist-info/RECORD
