Metadata-Version: 2.4
Name: trello_loader
Version: 0.1.0
Summary: A tool for loading Trello boards and converting them to Markdown for AI agents
Project-URL: Homepage, https://github.com/yourusername/trello_loader
Project-URL: Bug Tracker, https://github.com/yourusername/trello_loader/issues
Author-email: Eduard Götmann <e.goetmann@gmail.com>
License: MIT
License-File: LICENSE
Keywords: ai,conversion,markdown,trello
Classifier: License :: OSI Approved :: MIT License
Classifier: Operating System :: OS Independent
Classifier: Programming Language :: Python :: 3
Requires-Python: >=3.8
Requires-Dist: py-trello
Requires-Dist: python-dotenv
Requires-Dist: typer
